SpringKuangjiaRumenjiaochengCYuyanBianchengWang/README.md
SpringKuangjiaRumenjiaochengCYuyanBianchengWang/__init__.py
SpringKuangjiaRumenjiaochengCYuyanBianchengWang/__main__.py
SpringKuangjiaRumenjiaochengCYuyanBianchengWang/file.epub
SpringKuangjiaRumenjiaochengCYuyanBianchengWang/index.html
SpringKuangjiaRumenjiaochengCYuyanBianchengWang/css/__init__.py
SpringKuangjiaRumenjiaochengCYuyanBianchengWang/css/annotations.css
SpringKuangjiaRumenjiaochengCYuyanBianchengWang/css/main.css
SpringKuangjiaRumenjiaochengCYuyanBianchengWang/css/normalize.css
SpringKuangjiaRumenjiaochengCYuyanBianchengWang/css/popup.css
SpringKuangjiaRumenjiaochengCYuyanBianchengWang/font/__init__.py
SpringKuangjiaRumenjiaochengCYuyanBianchengWang/font/fontello.eot
SpringKuangjiaRumenjiaochengCYuyanBianchengWang/font/fontello.svg
SpringKuangjiaRumenjiaochengCYuyanBianchengWang/font/fontello.ttf
SpringKuangjiaRumenjiaochengCYuyanBianchengWang/font/fontello.woff
SpringKuangjiaRumenjiaochengCYuyanBianchengWang/img/__init__.py
SpringKuangjiaRumenjiaochengCYuyanBianchengWang/img/annotator-glyph-sprite.png
SpringKuangjiaRumenjiaochengCYuyanBianchengWang/img/annotator-icon-sprite.png
SpringKuangjiaRumenjiaochengCYuyanBianchengWang/img/apple-touch-icon.png
SpringKuangjiaRumenjiaochengCYuyanBianchengWang/img/cancelfullscreen.png
SpringKuangjiaRumenjiaochengCYuyanBianchengWang/img/close.png
SpringKuangjiaRumenjiaochengCYuyanBianchengWang/img/fullscreen.png
SpringKuangjiaRumenjiaochengCYuyanBianchengWang/img/loader.gif
SpringKuangjiaRumenjiaochengCYuyanBianchengWang/img/menu-icon.png
SpringKuangjiaRumenjiaochengCYuyanBianchengWang/img/save.png
SpringKuangjiaRumenjiaochengCYuyanBianchengWang/img/saved.png
SpringKuangjiaRumenjiaochengCYuyanBianchengWang/img/settings-s.png
SpringKuangjiaRumenjiaochengCYuyanBianchengWang/img/settings.png
SpringKuangjiaRumenjiaochengCYuyanBianchengWang/img/star.png
SpringKuangjiaRumenjiaochengCYuyanBianchengWang/js/__init__.py
spring_kuangjia_rumenjiaocheng_c_yuyan_biancheng_wang-2024.3.5.0.dist-info/METADATA
spring_kuangjia_rumenjiaocheng_c_yuyan_biancheng_wang-2024.3.5.0.dist-info/WHEEL
spring_kuangjia_rumenjiaocheng_c_yuyan_biancheng_wang-2024.3.5.0.dist-info/entry_points.txt
spring_kuangjia_rumenjiaocheng_c_yuyan_biancheng_wang-2024.3.5.0.dist-info/top_level.txt
spring_kuangjia_rumenjiaocheng_c_yuyan_biancheng_wang-2024.3.5.0.dist-info/RECORD
